[
  {"key": "Calli", "title": "Mori Calliope", "model_path": "SBV2_HoloLow", "speaker_id": "MoriCalliope", "language": "EN"},
  {"key": "Kiara", "title": "Takanashi Kiara", "model_path": "SBV2_TakanashiKiara", "speaker_id": "TakanashiKiara", "language": "EN"},
  {"key": "Ina", "title": "Ninomae Ina'nis", "model_path": "SBV2_HoloHi", "speaker_id": "NinomaeInanis", "language": "EN"},
  {"key": "Gura", "title": "Gawr Gura", "model_path": "SBV2_HoloHi", "speaker_id": "GawrGura", "language": "EN"},
  {"key": "Amelia", "title": "Amelia Watson", "model_path": "SBV2_HoloHi", "speaker_id": "AmeliaWatson", "language": "EN"},
  {"key": "IRyS", "title": "IRyS", "model_path": "SBV2_HoloHi", "speaker_id": "IRyS", "language": "EN"},
  {"key": "Sana", "title": "Tsukumo Sana", "model_path": "SBV2_HoloAus", "speaker_id": "TsukumoSana", "language": "EN"},
  {"key": "Fauna", "title": "Ceres Fauna", "model_path": "SBV2_HoloHi", "speaker_id": "CeresFauna", "language": "EN"},
  {"key": "Kronii", "title": "Ouro Kronii", "model_path": "SBV2_HoloLow", "speaker_id": "OuroKronii", "language": "EN"},
  {"key": "Mumei", "title": "Nanashi Mumei", "model_path": "SBV2_HoloHi", "speaker_id": "NanashiMumei", "language": "EN"},
  {"key": "Baelz", "title": "Hakos Baelz", "model_path": "SBV2_HoloAus", "speaker_id": "HakosBaelz", "language": "EN"},
  {"key": "Shiori", "title": "Shiori Novella", "model_path": "SBV2_HoloHi", "speaker_id": "ShioriNovella", "language": "EN"},
  {"key": "Bijou", "title": "Koseki Bijou", "model_path": "SBV2_KosekiBijou", "speaker_id": "KosekiBijou", "language": "EN"},
  {"key": "Nerissa", "title": "Nerissa Ravencroft", "model_path": "SBV2_HoloLow", "speaker_id": "NerissaRavencroft", "language": "EN"},
  {"key": "Iofi", "title": "Airani Iofifteen", "model_path": "SBV2_HoloESL", "speaker_id": "AiraniIofifteen", "language": "EN"},
  {"key": "Ollie", "title": "Kureiji Ollie", "model_path": "SBV2_HoloIDFlu", "speaker_id": "KureijiOllie", "language": "EN"},
  {"key": "Anya", "title": "Anya Melfissa", "model_path": "SBV2_HoloESL", "speaker_id": "AnyaMelfissa", "language": "EN"},
  {"key": "Zeta", "title": "Vestia Zeta", "model_path": "SBV2_HoloIDFlu", "speaker_id": "VestiaZeta", "language": "EN"},
  {"key": "Sora", "title": "Tokino Sora", "model_path": "SBV2_HoloJPTest2", "speaker_id": "TokinoSora", "language": "JP"},
  {"key": "Suisei", "title": "Hoshimachi Suisei", "model_path": "SBV2_HoloJPTest2", "speaker_id": "HoshimachiSuisei", "language": "JP"},
  {"key": "AZKi", "title": "AZKi", "model_path": "SBV2_HoloJPTest2.5", "speaker_id": "AZKi", "language": "JP"},
  {"key": "Mel", "title": "Yozora Mel", "model_path": "SBV2_HoloJPTest2.5", "speaker_id": "YozoraMel", "language": "JP"},
  {"key": "Matsuri", "title": "Natsuiro Matsuri", "model_path": "SBV2_HoloJPTest2.5", "speaker_id": "NatsuiroMatsuri", "language": "JP"},
  {"key": "Aki", "title": "Aki Rosenthal", "model_path": "SBV2_HoloJPTest2.5", "speaker_id": "AkiRosenthal", "language": "JP"},
  {"key": "Haato", "title": "Akai Haato", "model_path": "SBV2_HoloJPTest2.5", "speaker_id": "AkaiHaato", "language": "JP"},
  {"key": "Aqua", "title": "Minato Aqua", "model_path": "SBV2_HoloJPTest2", "speaker_id": "MinatoAqua", "language": "JP"},
  {"key": "Ayame", "title": "Nakiri Ayame", "model_path": "SBV2_HoloJPTest2", "speaker_id": "NakiriAyame", "language": "JP"},
  {"key": "Okayu", "title": "Nekomata Okayu", "model_path": "SBV2_HoloJPTest", "speaker_id": "NekomataOkayu", "language": "JP"},
  {"key": "Flare", "title": "Shiranui Flare", "model_path": "SBV2_HoloJPTest", "speaker_id": "ShiranuiFlare", "language": "JP"},
  {"key": "Noel", "title": "Shirogane Noel", "model_path": "SBV2_HoloJPTest", "speaker_id": "ShiroganeNoel", "language": "JP"},
  {"key": "Marine", "title": "Houshou Marine", "model_path": "SBV2_HoloJPTest", "speaker_id": "HoushouMarine", "language": "JP"},
  {"key": "Towa", "title": "Tokoyami Towa", "model_path": "SBV2_HoloJPTest2", "speaker_id": "TokoyamiTowa", "language": "JP"},
  {"key": "Lamy", "title": "Yukihana Lamy", "model_path": "SBV2_HoloJPTest2", "speaker_id": "YukihanaLamy", "language": "JP"},
  {"key": "Laplus", "title": "La+ Darknesss", "model_path": "SBV2_HoloJPTest", "speaker_id": "LaplusDarknesss", "language": "JP"},
  {"key": "Lui", "title": "Takane Lui", "model_path": "SBV2_HoloJPTest2.5", "speaker_id": "TakaneLui", "language": "JP"},
  {"key": "Koyori", "title": "Hakui Koyori", "model_path": "SBV2_HoloJPTest2", "speaker_id": "HakuiKoyori", "language": "JP"},
  {"key": "Chloe", "title": "Sakamata Chloe", "model_path": "SBV2_HoloJPTest2", "speaker_id": "SakamataChloe", "language": "JP"},
  {"key": "Ririka", "title": "Ichijou Ririka", "model_path": "SBV2_HoloJPTest", "speaker_id": "IchijouRirika", "language": "JP"}
]
